<?xml version="1.0" encoding="UTF-8"?>
<NFe xmlns="http://www.portalfiscal.inf.br/nfe">
  <infNFe Id="NFe354421920517760000010358439229682324737279" versao="4.00">
    <ide>
      <cUF>35</cUF>
      <cNF>58412365</cNF>
      <natOp>Prestacao de servico</natOp>
      <mod>55</mod>
      <serie>1</serie>
      <nNF>1035</nNF>
      <dhEmi>2026-01-20T15:43:00</dhEmi>
      <tpNF>1</tpNF>
      <idDest>1</idDest>
      <cMunFG>3550308</cMunFG>
      <tpImp>1</tpImp>
      <tpEmis>1</tpEmis>
      <finNFe>1</finNFe>
      <indFinal>1</indFinal>
      <indPres>1</indPres>
      <procEmi>0</procEmi>
      <verProc>1.0</verProc>
    </ide>

    <emit>
      <CNPJ>85296374000155</CNPJ>
      <xNome>Omega Sistemas SA</xNome>
      <enderEmit>
        <xLgr>Rua Exemplo</xLgr>
        <nro>119</nro>
        <xBairro>Centro</xBairro>
        <cMun>3550308</cMun>
        <xMun>Sao Paulo</xMun>
        <UF>SP</UF>
        <CEP>01000000</CEP>
        <cPais>1058</cPais>
        <xPais>Brasil</xPais>
      </enderEmit>
      <IE>198269319</IE>
      <CRT>3</CRT>
    </emit>

    <dest>
      <CNPJ>11222333000144</CNPJ>
      <xNome>Operadora Benefícios Saúde SA</xNome>
      <enderDest>
        <xLgr>Av Beneficios</xLgr>
        <nro>1000</nro>
        <xBairro>Paulista</xBairro>
        <cMun>3550308</cMun>
        <xMun>Sao Paulo</xMun>
        <UF>SP</UF>
        <CEP>01310000</CEP>
        <cPais>1058</cPais>
        <xPais>Brasil</xPais>
      </enderDest>
      <indIEDest>9</indIEDest>
    </dest>

    <det nItem="1">
      <prod>
        <cProd>ITEM105</cProd>
        <xProd>Consulta clínica</xProd>
        <CFOP>5933</CFOP>
        <uCom>UN</uCom>
        <qCom>1.0000</qCom>
        <vUnCom>5693.18</vUnCom>
        <vProd>5693.18</vProd>
      </prod>
    </det>

    <total>
      <ICMSTot>
        <vProd>5693.18</vProd>
        <vNF>5693.18</vNF>
      </ICMSTot>
    </total>

    <pag>
      <detPag>
        <tPag>90</tPag>
        <vPag>5693.18</vPag>
      </detPag>
    </pag>

    <infAdic>
      <infCpl>
usuario_envio=bruno.mendes |
paciente=João Martins |
cpf_paciente=44455566677 |
prestador=Hospital Vida Plena |
procedimento=Consulta clínica |
data_atendimento=2026-01-20 |
evento_clinico=Procedimento eletivo |
guia_atendimento=GUIA598216 |
lote=lote_01
      </infCpl>
    </infAdic>
  </infNFe>
</NFe>
